<?xml version="1.0" encoding="UTF-8"?>
<portlet-app xmlns="http://java.sun.com/xml/ns/portlet/portlet-app_1_0.xsd"
	version="1.0" xmlns:xsi="http://www.w3.org/2001/XMLSchema-instance"
	xsi:schemaLocation="http://java.sun.com/xml/ns/portlet/portlet-app_1_0.xsd http://java.sun.com/xml/ns/portlet/portlet-app_1_0.xsd">

  	<portlet>
		<description xml:lang="de">User-Status</description>
		<portlet-name>userStatus</portlet-name>
		<display-name xml:lang="de">User-Status</display-name>
		<portlet-class>org.springframework.web.portlet.DispatcherPortlet</portlet-class>
		<init-param>
			<name>contextConfigLocation</name>
			<value>/WEB-INF/context/userStatus.xml</value>
		</init-param>
		<expiration-cache>-1</expiration-cache>
		<supports>
			<mime-type>text/html</mime-type>
			<portlet-mode>view</portlet-mode>
		</supports>
		<supported-locale>en_US</supported-locale>
		<supported-locale>de_DE</supported-locale>
		<resource-bundle>de.uhh.l2g.resources.Resource</resource-bundle>
		<portlet-info>
			<title>User-Status</title>
			<short-title>User-Status</short-title>
			<keywords>User, Status</keywords>
		</portlet-info>
	</portlet>
	
</portlet-app>